pytest_redislite.py
pytest_redislite-0.1.0.dist-info/METADATA
pytest_redislite-0.1.0.dist-info/WHEEL
pytest_redislite-0.1.0.dist-info/entry_points.txt
pytest_redislite-0.1.0.dist-info/top_level.txt
pytest_redislite-0.1.0.dist-info/RECORD
