Metadata-Version: 2.1
Name: pytest-redislite
Version: 0.1.0
Summary: Pytest plugin for testing code using Redis
Home-page: https://github.com/klen/pytest-redislite
Author: Kirill Klenov
Author-email: horneds@gmail.com
License: MIT
Project-URL: Documentation, https://klen.github.io/pytest-redislite
Project-URL: Source code, https://github.com/klen/pytest-redislite
Project-URL: Issue tracker, https://github.com/klen/pytest-redislite/issues
Keywords: pytest,redis,redislite
Platform: UNKNOWN
Classifier: Development Status :: 4 - Beta
Classifier: Intended Audience :: Developers
Classifier: License :: OSI Approved :: MIT License
Classifier: Programming Language :: Python
Classifier: Programming Language :: Python :: 3
Classifier: Programming Language :: Python :: 3.7
Classifier: Programming Language :: Python :: 3.8
Classifier: Programming Language :: Python :: 3.9
Classifier: Programming Language :: Python :: 3.10
Classifier: Topic :: Software Development :: Testing
Classifier: Framework :: Pytest
Requires-Python: >=3.7
Requires-Dist: redislite
Requires-Dist: pytest
Provides-Extra: build
Requires-Dist: bump2version ; extra == 'build'
Provides-Extra: tests
Requires-Dist: redis ; extra == 'tests'
Requires-Dist: types-redis ; extra == 'tests'
Requires-Dist: pytest-mypy ; extra == 'tests'
